thingiverse/__init__.py
thingiverse/types/exceptions.py
thingiverse/types/search.py
python_thingiverse-0.0.5.dist-info/WHEEL
python_thingiverse-0.0.5.dist-info/METADATA
python_thingiverse-0.0.5.dist-info/RECORD
