Metadata-Version: 2.1
Name: python-thingiverse
Version: 0.0.5
Summary: A Python Thingiverse REST API wrapper
Home-page: https://garciajg.github.io/python-thingiverse/
Keywords: thingiverse,wrapper
Author: Jose Garcia
Author-email: maton.pg@gmail.com
Requires-Python: >=3.9,<4.0
Classifier: Programming Language :: Python :: 3
Requires-Dist: pytest (>=7.0.0,<8.0.0)
Requires-Dist: pytest-cov (>=3.0.0,<4.0.0)
Requires-Dist: python-box (>=5.4.1,<6.0.0)
Requires-Dist: requests (>=2.27.1,<3.0.0)
Requires-Dist: tox (>=3.24.5,<4.0.0)
Project-URL: Documentation, https://garciajg.github.io/python-thingiverse/
Project-URL: Repository, https://github.com/garciajg/python-thingiverse
